ritdu_slacker/__init__.py
ritdu_slacker/api.py
ritdu_slacker/cli.py
ritdu_slacker/formatter.py
ritdu_slacker/main.py
ritdu_slacker-1.5.2.dist-info/LICENSE
ritdu_slacker-1.5.2.dist-info/METADATA
ritdu_slacker-1.5.2.dist-info/WHEEL
ritdu_slacker-1.5.2.dist-info/entry_points.txt
ritdu_slacker-1.5.2.dist-info/RECORD
